{
  "id": "poi_685",
  "name": "Caspian's",
  "category": "nightlife",
  "subcategory": "bar_lounge",
  "casino_property": "Caesars Palace",
  "location": {
    "address": "3570 Las Vegas Blvd S, Las Vegas, NV 89109",
    "casino": "Caesars Palace",
    "coordinates": {
      "lat": 36.1162,
      "lng": -115.1744
    },
    "level": "ground",
    "area": "Mid Strip"
  },
  "contact": {
    "website": "https://www.smartervegas.com/nightlife/bars/caspians.aspx"
  },
  "description": "",
  "features": [
    "bar",
    "lounge",
    "cocktails"
  ],
  "tags": [
    "bar lounge",
    "nightlife",
    "las_vegas"
  ],
  "data_sources": [
    "smartervegas",
    "web_search_2026-02"
  ],
  "created_at": "2026-02-04T19:53:50Z",
  "updated_at": "2026-02-04T20:58:23Z",
  "pricing": {
    "price_range": "$$$"
  }
}